pyprud/__init__.py
pyprud/product.py
pyprud-0.1.1.dist-info/LICENSE
pyprud-0.1.1.dist-info/METADATA
pyprud-0.1.1.dist-info/WHEEL
pyprud-0.1.1.dist-info/RECORD
